MolAdsPy/__adsorption__.py
MolAdsPy/__atom__.py
MolAdsPy/__exception__.py
MolAdsPy/__init__.py
MolAdsPy/__molecule__.py
MolAdsPy/__slab__.py
MolAdsPy/__species__.py
MolAdsPy/core.py
MolAdsPy-0.1.1.dist-info/METADATA
MolAdsPy-0.1.1.dist-info/WHEEL
MolAdsPy-0.1.1.dist-info/top_level.txt
MolAdsPy-0.1.1.dist-info/RECORD
