Metadata-Version: 2.1
Name: MolAdsPy
Version: 0.1.1
Summary: Manipulation of molecules adsorbed on a substrate.
Home-page: https://github.com/rgaveiga/moladspy
Author: Roberto Gomes de Aguiar Veiga
License: UNKNOWN
Platform: UNKNOWN
Requires-Dist: multipledispatch
